<Properties StartupConfiguration="{5C66B0F8-FCF7-4461-8CB7-CA25548AB73E}|Default">
  <MonoDevelop.Ide.DebuggingService.PinnedWatches />
  <MonoDevelop.Ide.Workspace ActiveConfiguration="Debug" />
  <MonoDevelop.Ide.DebuggingService.Breakpoints>
    <BreakpointStore />
  </MonoDevelop.Ide.DebuggingService.Breakpoints>
  <MultiItemStartupConfigurations />
  <MonoDevelop.Ide.ItemProperties.CoreNRF PreferredExecutionTarget="/Applications/Google Chrome.app" />
  <MonoDevelop.Ide.Workbench ActiveDocument="CoreNRF/Api/RouteController.cs">
    <Files>
      <File FileName="CoreNRF/Api/RouteController.cs" Line="54" Column="51" />
      <File FileName="CoreNRF/Dtos/ServiceDto/ServiceReqstDto.cs" Line="15" Column="1" />
      <File FileName="CoreNRF/Services/ServicesService/ServicesService.cs" Line="43" Column="47" />
      <File FileName="CoreNRF/Models/NF.cs" Line="14" Column="65" />
      <File FileName="CoreNRF/Models/PortalNF.cs" Line="6" Column="6" />
      <File FileName="CoreNRF/Dtos/NRFDto/IncomeNFDto.cs" Line="8" Column="29" />
      <File FileName="CoreNRF/Services/NFService/NFService.cs" Line="1" Column="1" />
    </Files>
    <Pads>
      <Pad Id="ProjectPad">
        <State name="__root__">
          <Node name="CoreNRF" expanded="True">
            <Node name="CoreNRF" expanded="True">
              <Node name="Api" expanded="True" />
              <Node name="Controllers" expanded="True" />
              <Node name="Data" expanded="True" />
              <Node name="Dtos" expanded="True">
                <Node name="NRFDto" expanded="True" />
                <Node name="ServiceDto" expanded="True" />
              </Node>
              <Node name="Migrations" expanded="True" />
              <Node name="Models" expanded="True" />
              <Node name="Services" expanded="True">
                <Node name="LocationService" expanded="True" />
                <Node name="NFService" expanded="True" />
                <Node name="NFServService" expanded="True" />
                <Node name="ServicesService" expanded="True" />
              </Node>
              <Node name="Utils" expanded="True" />
            </Node>
          </Node>
        </State>
      </Pad>
      <Pad Id="MonoDevelop.Debugger.WatchPad">
        <State />
      </Pad>
    </Pads>
  </MonoDevelop.Ide.Workbench>
</Properties>